muerte32crypt/__init__.py
muerte32crypt/certs.py
muerte32crypt/compression.py
muerte32crypt/curves.py
muerte32crypt/dpapi.py
muerte32crypt/keymanagement.py
muerte32crypt/securestorage.py
muerte32crypt/tpm.py
muerte32crypt/utils.py
muerte32crypt-1.0.8.dist-info/METADATA
muerte32crypt-1.0.8.dist-info/WHEEL
muerte32crypt-1.0.8.dist-info/top_level.txt
muerte32crypt-1.0.8.dist-info/RECORD
