Metadata-Version: 2.4
Name: muerte32crypt
Version: 1.0.8
Summary: Windows-native DPAPI encryption with a clean Python interface.
Author-email: MuerteSeguraZ <northkoreanukeslmao@gmail.com>
License: MIT
Keywords: dpapi,windows,encryption,crypto
Classifier: Programming Language :: Python :: 3
Classifier: Operating System :: Microsoft :: Windows
Classifier: License :: OSI Approved :: MIT License
Classifier: Topic :: Security :: Cryptography
Requires-Python: >=3.7
